CHANGELOG.txt
LICENSE.txt
MANIFEST.in
README.txt
ez_setup.py
setup.py
palb/__init__.py
palb/core.py
palb/stats.py
palb.egg-info/PKG-INFO
palb.egg-info/SOURCES.txt
palb.egg-info/dependency_links.txt
palb.egg-info/entry_points.txt
palb.egg-info/not-zip-safe
palb.egg-info/top_level.txt
palb/getter/__init__.py
palb/getter/curl.py
palb/getter/urllib.py
tests/__init__.py
tests/http.py
tests/test_curl.py
tests/test_stats.py
tests/test_urllib.py