Metadata-Version: 1.0
Name: palb
Version: 0.1.1
Summary: Python Apache-Like Benchmark Tool
Home-page: UNKNOWN
Author: Oliver Tonnhofer
Author-email: olt@bogosoft.com
License: Copyright (c) 2009 Oliver Tonnhofer <olt@bogosoft.com>
